{
  "id": "root-1010",
  "type": "frame",
  "name": "A9. Superadmin: Смены",
  "width": 1280,
  "height": 800,
  "layout": "horizontal",
  "gap": 0,
  "padding": 0,
  "fill": [
    {
      "type": "solid",
      "color": "#F5F5F7"
    }
  ],
  "clipContent": true,
  "children": [
    {
      "id": "sb-1011",
      "type": "frame",
      "name": "Sidebar",
      "width": 220,
      "height": "fill_container",
      "layout": "vertical",
      "gap": 6,
      "padding": 16,
      "fill": [
        {
          "type": "solid",
          "color": "#FAFAFC"
        }
      ],
      "stroke": {
        "thickness": 0,
        "fill": [
          {
            "type": "solid",
            "color": "#D0D0D5"
          }
        ]
      },
      "children": [
        {
          "id": "plain-1015",
          "type": "frame",
          "width": "fill_container",
          "height": "fit_content",
          "layout": "horizontal",
          "gap": 8,
          "padding": [
            12,
            8
          ],
          "alignItems": "center",
          "children": [
            {
              "id": "ph-1012",
              "type": "frame",
              "width": 28,
              "height": 28,
              "layout": "horizontal",
              "alignItems": "center",
              "justifyContent": "center",
              "fill": [
                {
                  "type": "solid",
                  "color": "#FAFAFC"
                }
              ],
              "stroke": {
                "thickness": 1,
                "fill": [
                  {
                    "type": "solid",
                    "color": "#B0B0B5"
                  }
                ]
              },
              "cornerRadius": 6,
              "children": [
                {
                  "id": "t-1013",
                  "type": "text",
                  "content": "LOGO",
                  "fontFamily": "Roboto",
                  "fontSize": 11,
                  "fontWeight": 400,
                  "fill": [
                    {
                      "type": "solid",
                      "color": "#B0B0B5"
                    }
                  ]
                }
              ]
            },
            {
              "id": "t-1014",
              "type": "text",
              "content": "SUPERADMIN",
              "fontFamily": "Roboto",
              "fontSize": 12,
              "fontWeight": 700,
              "fill": [
                {
                  "type": "solid",
                  "color": "#2C2C2E"
                }
              ]
            }
          ]
        },
        {
          "id": "div-1016",
          "type": "rectangle",
          "width": "fill_container",
          "height": 1,
          "fill": [
            {
              "type": "solid",
              "color": "#D0D0D5"
            }
          ]
        },
        {
          "id": "t-1017",
          "type": "text",
          "content": "УПРАВЛЕНИЕ",
          "fontFamily": "Roboto",
          "fontSize": 11,
          "fontWeight": 400,
          "fill": [
            {
              "type": "solid",
              "color": "#6C6C72"
            }
          ]
        },
        {
          "id": "nav-1018",
          "type": "frame",
          "width": "fill_container",
          "height": 36,
          "padding": [
            8,
            12
          ],
          "layout": "horizontal",
          "alignItems": "center",
          "fill": [
            {
              "type": "solid",
              "color": "#EAEAEE"
            }
          ],
          "cornerRadius": 6,
          "children": [
            {
              "id": "t-1019",
              "type": "text",
              "content": "Смены",
              "fontFamily": "Roboto",
              "fontSize": 13,
              "fontWeight": 600,
              "fill": [
                {
                  "type": "solid",
                  "color": "#2C2C2E"
                }
              ]
            }
          ]
        },
        {
          "id": "nav-1020",
          "type": "frame",
          "width": "fill_container",
          "height": 36,
          "padding": [
            8,
            12
          ],
          "layout": "horizontal",
          "alignItems": "center",
          "fill": [
            {
              "type": "solid",
              "color": "#00000000"
            }
          ],
          "cornerRadius": 6,
          "children": [
            {
              "id": "t-1021",
              "type": "text",
              "content": "Роли и Ачивки",
              "fontFamily": "Roboto",
              "fontSize": 13,
              "fontWeight": 400,
              "fill": [
                {
                  "type": "solid",
                  "color": "#6C6C72"
                }
              ]
            }
          ]
        },
        {
          "id": "nav-1022",
          "type": "frame",
          "width": "fill_container",
          "height": 36,
          "padding": [
            8,
            12
          ],
          "layout": "horizontal",
          "alignItems": "center",
          "fill": [
            {
              "type": "solid",
              "color": "#00000000"
            }
          ],
          "cornerRadius": 6,
          "children": [
            {
              "id": "t-1023",
              "type": "text",
              "content": "Экспорт",
              "fontFamily": "Roboto",
              "fontSize": 13,
              "fontWeight": 400,
              "fill": [
                {
                  "type": "solid",
                  "color": "#6C6C72"
                }
              ]
            }
          ]
        },
        {
          "id": "nav-1024",
          "type": "frame",
          "width": "fill_container",
          "height": 36,
          "padding": [
            8,
            12
          ],
          "layout": "horizontal",
          "alignItems": "center",
          "fill": [
            {
              "type": "solid",
              "color": "#00000000"
            }
          ],
          "cornerRadius": 6,
          "children": [
            {
              "id": "t-1025",
              "type": "text",
              "content": "Статистика",
              "fontFamily": "Roboto",
              "fontSize": 13,
              "fontWeight": 400,
              "fill": [
                {
                  "type": "solid",
                  "color": "#6C6C72"
                }
              ]
            }
          ]
        },
        {
          "id": "div-1026",
          "type": "rectangle",
          "width": "fill_container",
          "height": 1,
          "fill": [
            {
              "type": "solid",
              "color": "#D0D0D5"
            }
          ]
        },
        {
          "id": "t-1027",
          "type": "text",
          "content": "АККАУНТ",
          "fontFamily": "Roboto",
          "fontSize": 11,
          "fontWeight": 400,
          "fill": [
            {
              "type": "solid",
              "color": "#6C6C72"
            }
          ]
        },
        {
          "id": "nav-1028",
          "type": "frame",
          "width": "fill_container",
          "height": 36,
          "padding": [
            8,
            12
          ],
          "layout": "horizontal",
          "alignItems": "center",
          "fill": [
            {
              "type": "solid",
              "color": "#00000000"
            }
          ],
          "cornerRadius": 6,
          "children": [
            {
              "id": "t-1029",
              "type": "text",
              "content": "Выход",
              "fontFamily": "Roboto",
              "fontSize": 13,
              "fontWeight": 400,
              "fill": [
                {
                  "type": "solid",
                  "color": "#6C6C72"
                }
              ]
            }
          ]
        }
      ]
    },
    {
      "id": "plain-1030",
      "type": "frame",
      "width": "fill_container",
      "height": "fill_container",
      "layout": "vertical",
      "gap": 0,
      "padding": 0,
      "children": [
        {
          "id": "plain-925",
          "type": "frame",
          "width": "fill_container",
          "height": 60,
          "layout": "horizontal",
          "gap": 8,
          "padding": [
            0,
            24
          ],
          "alignItems": "center",
          "justifyContent": "space_between",
          "children": [
            {
              "id": "plain-920",
              "type": "frame",
              "width": "fit_content",
              "height": "fit_content",
              "layout": "horizontal",
              "gap": 8,
              "padding": 0,
              "alignItems": "center",
              "children": [
                {
                  "id": "t-917",
                  "type": "text",
                  "content": "Superadmin",
                  "fontFamily": "Roboto",
                  "fontSize": 13,
                  "fontWeight": 400,
                  "fill": [
                    {
                      "type": "solid",
                      "color": "#6C6C72"
                    }
                  ]
                },
                {
                  "id": "t-918",
                  "type": "text",
                  "content": "›",
                  "fontFamily": "Roboto",
                  "fontSize": 14,
                  "fontWeight": 400,
                  "fill": [
                    {
                      "type": "solid",
                      "color": "#6C6C72"
                    }
                  ]
                },
                {
                  "id": "t-919",
                  "type": "text",
                  "content": "Смены",
                  "fontFamily": "Roboto",
                  "fontSize": 13,
                  "fontWeight": 700,
                  "fill": [
                    {
                      "type": "solid",
                      "color": "#2C2C2E"
                    }
                  ]
                }
              ]
            },
            {
              "id": "plain-924",
              "type": "frame",
              "width": "fit_content",
              "height": "fit_content",
              "layout": "horizontal",
              "gap": 8,
              "padding": 0,
              "alignItems": "center",
              "children": [
                {
                  "id": "t-921",
                  "type": "text",
                  "content": "Иван П. • Продюсер",
                  "fontFamily": "Roboto",
                  "fontSize": 11,
                  "fontWeight": 400,
                  "fill": [
                    {
                      "type": "solid",
                      "color": "#6C6C72"
                    }
                  ]
                },
                {
                  "id": "ph-922",
                  "type": "frame",
                  "width": 32,
                  "height": 32,
                  "layout": "horizontal",
                  "alignItems": "center",
                  "justifyContent": "center",
                  "fill": [
                    {
                      "type": "solid",
                      "color": "#FAFAFC"
                    }
                  ],
                  "stroke": {
                    "thickness": 1,
                    "fill": [
                      {
                        "type": "solid",
                        "color": "#B0B0B5"
                      }
                    ]
                  },
                  "cornerRadius": 6,
                  "children": [
                    {
                      "id": "t-923",
                      "type": "text",
                      "content": "AV",
                      "fontFamily": "Roboto",
                      "fontSize": 11,
                      "fontWeight": 400,
                      "fill": [
                        {
                          "type": "solid",
                          "color": "#B0B0B5"
                        }
                      ]
                    }
                  ]
                }
              ]
            }
          ]
        },
        {
          "id": "plain-1009",
          "type": "frame",
          "width": "fill_container",
          "height": "fit_content",
          "layout": "vertical",
          "gap": 20,
          "padding": 24,
          "children": [
            {
              "id": "plain-929",
              "type": "frame",
              "width": "fill_container",
              "height": "fit_content",
              "layout": "horizontal",
              "gap": 8,
              "padding": 0,
              "alignItems": "center",
              "justifyContent": "space_between",
              "children": [
                {
                  "id": "t-926",
                  "type": "text",
                  "content": "Все смены",
                  "fontFamily": "Roboto",
                  "fontSize": 22,
                  "fontWeight": 700,
                  "fill": [
                    {
                      "type": "solid",
                      "color": "#2C2C2E"
                    }
                  ]
                },
                {
                  "id": "btn-927",
                  "type": "frame",
                  "role": "button",
                  "width": "fit_content",
                  "height": 36,
                  "padding": [
                    8,
                    16
                  ],
                  "layout": "horizontal",
                  "alignItems": "center",
                  "justifyContent": "center",
                  "fill": [
                    {
                      "type": "solid",
                      "color": "#2C2C2E"
                    }
                  ],
                  "stroke": {
                    "thickness": 1,
                    "fill": [
                      {
                        "type": "solid",
                        "color": "#2C2C2E"
                      }
                    ]
                  },
                  "cornerRadius": 6,
                  "children": [
                    {
                      "id": "t-928",
                      "type": "text",
                      "content": "+ Новая смена",
                      "fontFamily": "Roboto",
                      "fontSize": 12,
                      "fontWeight": 600,
                      "fill": [
                        {
                          "type": "solid",
                          "color": "#FFF"
                        }
                      ]
                    }
                  ]
                }
              ]
            },
            {
              "id": "box-977",
              "type": "frame",
              "width": "fill_container",
              "height": "fit_content",
              "layout": "vertical",
              "gap": 12,
              "padding": 16,
              "fill": [
                {
                  "type": "solid",
                  "color": "#FFFFFF"
                }
              ],
              "stroke": {
                "thickness": 1,
                "fill": [
                  {
                    "type": "solid",
                    "color": "#D0D0D5"
                  }
                ]
              },
              "cornerRadius": 6,
              "children": [
                {
                  "id": "plain-939",
                  "type": "frame",
                  "width": "fill_container",
                  "height": "fit_content",
                  "layout": "horizontal",
                  "gap": 8,
                  "padding": [
                    8,
                    12
                  ],
                  "children": [
                    {
                      "id": "t-930",
                      "type": "text",
                      "content": "НАЗВАНИЕ",
                      "fontFamily": "Roboto",
                      "fontSize": 11,
                      "fontWeight": 400,
                      "fill": [
                        {
                          "type": "solid",
                          "color": "#6C6C72"
                        }
                      ]
                    },
                    {
                      "id": "t-931",
                      "type": "text",
                      "content": "",
                      "fontFamily": "Roboto",
                      "fontSize": 13,
                      "fontWeight": 400,
                      "fill": [
                        {
                          "type": "solid",
                          "color": "#2C2C2E"
                        }
                      ],
                      "width": 320
                    },
                    {
                      "id": "t-932",
                      "type": "text",
                      "content": "ДАТЫ",
                      "fontFamily": "Roboto",
                      "fontSize": 11,
                      "fontWeight": 400,
                      "fill": [
                        {
                          "type": "solid",
                          "color": "#6C6C72"
                        }
                      ]
                    },
                    {
                      "id": "t-933",
                      "type": "text",
                      "content": "",
                      "fontFamily": "Roboto",
                      "fontSize": 13,
                      "fontWeight": 400,
                      "fill": [
                        {
                          "type": "solid",
                          "color": "#2C2C2E"
                        }
                      ],
                      "width": 200
                    },
                    {
                      "id": "t-934",
                      "type": "text",
                      "content": "УЧАСТНИКОВ",
                      "fontFamily": "Roboto",
                      "fontSize": 11,
                      "fontWeight": 400,
                      "fill": [
                        {
                          "type": "solid",
                          "color": "#6C6C72"
                        }
                      ]
                    },
                    {
                      "id": "t-935",
                      "type": "text",
                      "content": "",
                      "fontFamily": "Roboto",
                      "fontSize": 13,
                      "fontWeight": 400,
                      "fill": [
                        {
                          "type": "solid",
                          "color": "#2C2C2E"
                        }
                      ],
                      "width": 120
                    },
                    {
                      "id": "t-936",
                      "type": "text",
                      "content": "СТАТУС",
                      "fontFamily": "Roboto",
                      "fontSize": 11,
                      "fontWeight": 400,
                      "fill": [
                        {
                          "type": "solid",
                          "color": "#6C6C72"
                        }
                      ]
                    },
                    {
                      "id": "t-937",
                      "type": "text",
                      "content": "",
                      "fontFamily": "Roboto",
                      "fontSize": 13,
                      "fontWeight": 400,
                      "fill": [
                        {
                          "type": "solid",
                          "color": "#2C2C2E"
                        }
                      ],
                      "width": 120
                    },
                    {
                      "id": "t-938",
                      "type": "text",
                      "content": "ДЕЙСТВИЯ",
                      "fontFamily": "Roboto",
                      "fontSize": 11,
                      "fontWeight": 400,
                      "fill": [
                        {
                          "type": "solid",
                          "color": "#6C6C72"
                        }
                      ]
                    }
                  ]
                },
                {
                  "id": "div-940",
                  "type": "rectangle",
                  "width": "fill_container",
                  "height": 1,
                  "fill": [
                    {
                      "type": "solid",
                      "color": "#D0D0D5"
                    }
                  ]
                },
                {
                  "id": "plain-952",
                  "type": "frame",
                  "width": "fill_container",
                  "height": "fit_content",
                  "layout": "horizontal",
                  "gap": 8,
                  "padding": [
                    12,
                    12
                  ],
                  "alignItems": "center",
                  "children": [
                    {
                      "id": "t-941",
                      "type": "text",
                      "content": "ТЕЛЕМОРЕ Лето 2026",
                      "fontFamily": "Roboto",
                      "fontSize": 13,
                      "fontWeight": 600,
                      "fill": [
                        {
                          "type": "solid",
                          "color": "#2C2C2E"
                        }
                      ],
                      "width": 320
                    },
                    {
                      "id": "t-942",
                      "type": "text",
                      "content": "10.06 – 23.06",
                      "fontFamily": "Roboto",
                      "fontSize": 13,
                      "fontWeight": 400,
                      "fill": [
                        {
                          "type": "solid",
                          "color": "#2C2C2E"
                        }
                      ],
                      "width": 200
                    },
                    {
                      "id": "t-943",
                      "type": "text",
                      "content": "60",
                      "fontFamily": "Roboto",
                      "fontSize": 13,
                      "fontWeight": 400,
                      "fill": [
                        {
                          "type": "solid",
                          "color": "#2C2C2E"
                        }
                      ],
                      "width": 120
                    },
                    {
                      "id": "t-944",
                      "type": "text",
                      "content": "Активна",
                      "fontFamily": "Roboto",
                      "fontSize": 13,
                      "fontWeight": 400,
                      "fill": [
                        {
                          "type": "solid",
                          "color": "#2C2C2E"
                        }
                      ],
                      "width": 120
                    },
                    {
                      "id": "plain-951",
                      "type": "frame",
                      "width": "fit_content",
                      "height": "fit_content",
                      "layout": "horizontal",
                      "gap": 6,
                      "padding": 0,
                      "children": [
                        {
                          "id": "btn-945",
                          "type": "frame",
                          "role": "button",
                          "width": "fit_content",
                          "height": 28,
                          "padding": [
                            8,
                            16
                          ],
                          "layout": "horizontal",
                          "alignItems": "center",
                          "justifyContent": "center",
                          "fill": [
                            {
                              "type": "solid",
                              "color": "#FFFFFF"
                            }
                          ],
                          "stroke": {
                            "thickness": 1,
                            "fill": [
                              {
                                "type": "solid",
                                "color": "#D0D0D5"
                              }
                            ]
                          },
                          "cornerRadius": 6,
                          "children": [
                            {
                              "id": "t-946",
                              "type": "text",
                              "content": "Открыть",
                              "fontFamily": "Roboto",
                              "fontSize": 12,
                              "fontWeight": 600,
                              "fill": [
                                {
                                  "type": "solid",
                                  "color": "#2C2C2E"
                                }
                              ]
                            }
                          ]
                        },
                        {
                          "id": "btn-947",
                          "type": "frame",
                          "role": "button",
                          "width": "fit_content",
                          "height": 28,
                          "padding": [
                            8,
                            16
                          ],
                          "layout": "horizontal",
                          "alignItems": "center",
                          "justifyContent": "center",
                          "fill": [
                            {
                              "type": "solid",
                              "color": "#FFFFFF"
                            }
                          ],
                          "stroke": {
                            "thickness": 1,
                            "fill": [
                              {
                                "type": "solid",
                                "color": "#D0D0D5"
                              }
                            ]
                          },
                          "cornerRadius": 6,
                          "children": [
                            {
                              "id": "t-948",
                              "type": "text",
                              "content": "Копировать",
                              "fontFamily": "Roboto",
                              "fontSize": 12,
                              "fontWeight": 600,
                              "fill": [
                                {
                                  "type": "solid",
                                  "color": "#2C2C2E"
                                }
                              ]
                            }
                          ]
                        },
                        {
                          "id": "btn-949",
                          "type": "frame",
                          "role": "button",
                          "width": "fit_content",
                          "height": 28,
                          "padding": [
                            8,
                            16
                          ],
                          "layout": "horizontal",
                          "alignItems": "center",
                          "justifyContent": "center",
                          "fill": [
                            {
                              "type": "solid",
                              "color": "#FFFFFF"
                            }
                          ],
                          "stroke": {
                            "thickness": 1,
                            "fill": [
                              {
                                "type": "solid",
                                "color": "#D0D0D5"
                              }
                            ]
                          },
                          "cornerRadius": 6,
                          "children": [
                            {
                              "id": "t-950",
                              "type": "text",
                              "content": "Архив",
                              "fontFamily": "Roboto",
                              "fontSize": 12,
                              "fontWeight": 600,
                              "fill": [
                                {
                                  "type": "solid",
                                  "color": "#2C2C2E"
                                }
                              ]
                            }
                          ]
                        }
                      ]
                    }
                  ]
                },
                {
                  "id": "plain-964",
                  "type": "frame",
                  "width": "fill_container",
                  "height": "fit_content",
                  "layout": "horizontal",
                  "gap": 8,
                  "padding": [
                    12,
                    12
                  ],
                  "alignItems": "center",
                  "children": [
                    {
                      "id": "t-953",
                      "type": "text",
                      "content": "ТЕЛЕМОРЕ Зима 2025",
                      "fontFamily": "Roboto",
                      "fontSize": 13,
                      "fontWeight": 600,
                      "fill": [
                        {
                          "type": "solid",
                          "color": "#2C2C2E"
                        }
                      ],
                      "width": 320
                    },
                    {
                      "id": "t-954",
                      "type": "text",
                      "content": "05.12 – 18.12",
                      "fontFamily": "Roboto",
                      "fontSize": 13,
                      "fontWeight": 400,
                      "fill": [
                        {
                          "type": "solid",
                          "color": "#2C2C2E"
                        }
                      ],
                      "width": 200
                    },
                    {
                      "id": "t-955",
                      "type": "text",
                      "content": "45",
                      "fontFamily": "Roboto",
                      "fontSize": 13,
                      "fontWeight": 400,
                      "fill": [
                        {
                          "type": "solid",
                          "color": "#2C2C2E"
                        }
                      ],
                      "width": 120
                    },
                    {
                      "id": "t-956",
                      "type": "text",
                      "content": "Завершена",
                      "fontFamily": "Roboto",
                      "fontSize": 13,
                      "fontWeight": 400,
                      "fill": [
                        {
                          "type": "solid",
                          "color": "#2C2C2E"
                        }
                      ],
                      "width": 120
                    },
                    {
                      "id": "plain-963",
                      "type": "frame",
                      "width": "fit_content",
                      "height": "fit_content",
                      "layout": "horizontal",
                      "gap": 6,
                      "padding": 0,
                      "children": [
                        {
                          "id": "btn-957",
                          "type": "frame",
                          "role": "button",
                          "width": "fit_content",
                          "height": 28,
                          "padding": [
                            8,
                            16
                          ],
                          "layout": "horizontal",
                          "alignItems": "center",
                          "justifyContent": "center",
                          "fill": [
                            {
                              "type": "solid",
                              "color": "#FFFFFF"
                            }
                          ],
                          "stroke": {
                            "thickness": 1,
                            "fill": [
                              {
                                "type": "solid",
                                "color": "#D0D0D5"
                              }
                            ]
                          },
                          "cornerRadius": 6,
                          "children": [
                            {
                              "id": "t-958",
                              "type": "text",
                              "content": "Открыть",
                              "fontFamily": "Roboto",
                              "fontSize": 12,
                              "fontWeight": 600,
                              "fill": [
                                {
                                  "type": "solid",
                                  "color": "#2C2C2E"
                                }
                              ]
                            }
                          ]
                        },
                        {
                          "id": "btn-959",
                          "type": "frame",
                          "role": "button",
                          "width": "fit_content",
                          "height": 28,
                          "padding": [
                            8,
                            16
                          ],
                          "layout": "horizontal",
                          "alignItems": "center",
                          "justifyContent": "center",
                          "fill": [
                            {
                              "type": "solid",
                              "color": "#FFFFFF"
                            }
                          ],
                          "stroke": {
                            "thickness": 1,
                            "fill": [
                              {
                                "type": "solid",
                                "color": "#D0D0D5"
                              }
                            ]
                          },
                          "cornerRadius": 6,
                          "children": [
                            {
                              "id": "t-960",
                              "type": "text",
                              "content": "Копировать",
                              "fontFamily": "Roboto",
                              "fontSize": 12,
                              "fontWeight": 600,
                              "fill": [
                                {
                                  "type": "solid",
                                  "color": "#2C2C2E"
                                }
                              ]
                            }
                          ]
                        },
                        {
                          "id": "btn-961",
                          "type": "frame",
                          "role": "button",
                          "width": "fit_content",
                          "height": 28,
                          "padding": [
                            8,
                            16
                          ],
                          "layout": "horizontal",
                          "alignItems": "center",
                          "justifyContent": "center",
                          "fill": [
                            {
                              "type": "solid",
                              "color": "#FFFFFF"
                            }
                          ],
                          "stroke": {
                            "thickness": 1,
                            "fill": [
                              {
                                "type": "solid",
                                "color": "#D0D0D5"
                              }
                            ]
                          },
                          "cornerRadius": 6,
                          "children": [
                            {
                              "id": "t-962",
                              "type": "text",
                              "content": "Архив",
                              "fontFamily": "Roboto",
                              "fontSize": 12,
                              "fontWeight": 600,
                              "fill": [
                                {
                                  "type": "solid",
                                  "color": "#2C2C2E"
                                }
                              ]
                            }
                          ]
                        }
                      ]
                    }
                  ]
                },
                {
                  "id": "plain-976",
                  "type": "frame",
                  "width": "fill_container",
                  "height": "fit_content",
                  "layout": "horizontal",
                  "gap": 8,
                  "padding": [
                    12,
                    12
                  ],
                  "alignItems": "center",
                  "children": [
                    {
                      "id": "t-965",
                      "type": "text",
                      "content": "ТЕЛЕМОРЕ Осень 2025",
                      "fontFamily": "Roboto",
                      "fontSize": 13,
                      "fontWeight": 600,
                      "fill": [
                        {
                          "type": "solid",
                          "color": "#2C2C2E"
                        }
                      ],
                      "width": 320
                    },
                    {
                      "id": "t-966",
                      "type": "text",
                      "content": "15.09 – 28.09",
                      "fontFamily": "Roboto",
                      "fontSize": 13,
                      "fontWeight": 400,
                      "fill": [
                        {
                          "type": "solid",
                          "color": "#2C2C2E"
                        }
                      ],
                      "width": 200
                    },
                    {
                      "id": "t-967",
                      "type": "text",
                      "content": "55",
                      "fontFamily": "Roboto",
                      "fontSize": 13,
                      "fontWeight": 400,
                      "fill": [
                        {
                          "type": "solid",
                          "color": "#2C2C2E"
                        }
                      ],
                      "width": 120
                    },
                    {
                      "id": "t-968",
                      "type": "text",
                      "content": "Завершена",
                      "fontFamily": "Roboto",
                      "fontSize": 13,
                      "fontWeight": 400,
                      "fill": [
                        {
                          "type": "solid",
                          "color": "#2C2C2E"
                        }
                      ],
                      "width": 120
                    },
                    {
                      "id": "plain-975",
                      "type": "frame",
                      "width": "fit_content",
                      "height": "fit_content",
                      "layout": "horizontal",
                      "gap": 6,
                      "padding": 0,
                      "children": [
                        {
                          "id": "btn-969",
                          "type": "frame",
                          "role": "button",
                          "width": "fit_content",
                          "height": 28,
                          "padding": [
                            8,
                            16
                          ],
                          "layout": "horizontal",
                          "alignItems": "center",
                          "justifyContent": "center",
                          "fill": [
                            {
                              "type": "solid",
                              "color": "#FFFFFF"
                            }
                          ],
                          "stroke": {
                            "thickness": 1,
                            "fill": [
                              {
                                "type": "solid",
                                "color": "#D0D0D5"
                              }
                            ]
                          },
                          "cornerRadius": 6,
                          "children": [
                            {
                              "id": "t-970",
                              "type": "text",
                              "content": "Открыть",
                              "fontFamily": "Roboto",
                              "fontSize": 12,
                              "fontWeight": 600,
                              "fill": [
                                {
                                  "type": "solid",
                                  "color": "#2C2C2E"
                                }
                              ]
                            }
                          ]
                        },
                        {
                          "id": "btn-971",
                          "type": "frame",
                          "role": "button",
                          "width": "fit_content",
                          "height": 28,
                          "padding": [
                            8,
                            16
                          ],
                          "layout": "horizontal",
                          "alignItems": "center",
                          "justifyContent": "center",
                          "fill": [
                            {
                              "type": "solid",
                              "color": "#FFFFFF"
                            }
                          ],
                          "stroke": {
                            "thickness": 1,
                            "fill": [
                              {
                                "type": "solid",
                                "color": "#D0D0D5"
                              }
                            ]
                          },
                          "cornerRadius": 6,
                          "children": [
                            {
                              "id": "t-972",
                              "type": "text",
                              "content": "Копировать",
                              "fontFamily": "Roboto",
                              "fontSize": 12,
                              "fontWeight": 600,
                              "fill": [
                                {
                                  "type": "solid",
                                  "color": "#2C2C2E"
                                }
                              ]
                            }
                          ]
                        },
                        {
                          "id": "btn-973",
                          "type": "frame",
                          "role": "button",
                          "width": "fit_content",
                          "height": 28,
                          "padding": [
                            8,
                            16
                          ],
                          "layout": "horizontal",
                          "alignItems": "center",
                          "justifyContent": "center",
                          "fill": [
                            {
                              "type": "solid",
                              "color": "#FFFFFF"
                            }
                          ],
                          "stroke": {
                            "thickness": 1,
                            "fill": [
                              {
                                "type": "solid",
                                "color": "#D0D0D5"
                              }
                            ]
                          },
                          "cornerRadius": 6,
                          "children": [
                            {
                              "id": "t-974",
                              "type": "text",
                              "content": "Архив",
                              "fontFamily": "Roboto",
                              "fontSize": 12,
                              "fontWeight": 600,
                              "fill": [
                                {
                                  "type": "solid",
                                  "color": "#2C2C2E"
                                }
                              ]
                            }
                          ]
                        }
                      ]
                    }
                  ]
                }
              ]
            },
            {
              "id": "box-1008",
              "type": "frame",
              "width": "fill_container",
              "height": "fit_content",
              "layout": "vertical",
              "gap": 12,
              "padding": 20,
              "fill": [
                {
                  "type": "solid",
                  "color": "#FFFFFF"
                }
              ],
              "stroke": {
                "thickness": 1,
                "fill": [
                  {
                    "type": "solid",
                    "color": "#D0D0D5"
                  }
                ]
              },
              "cornerRadius": 6,
              "children": [
                {
                  "id": "t-978",
                  "type": "text",
                  "content": "Создать новую смену",
                  "fontFamily": "Roboto",
                  "fontSize": 15,
                  "fontWeight": 700,
                  "fill": [
                    {
                      "type": "solid",
                      "color": "#2C2C2E"
                    }
                  ]
                },
                {
                  "id": "plain-985",
                  "type": "frame",
                  "width": "fill_container",
                  "height": "fit_content",
                  "layout": "horizontal",
                  "gap": 12,
                  "padding": 0,
                  "children": [
                    {
                      "id": "box-981",
                      "type": "frame",
                      "width": "fill_container",
                      "height": "fit_content",
                      "layout": "vertical",
                      "gap": 12,
                      "padding": 16,
                      "fill": [
                        {
                          "type": "solid",
                          "color": "#FAFAFC"
                        }
                      ],
                      "stroke": {
                        "thickness": 1,
                        "fill": [
                          {
                            "type": "solid",
                            "color": "#D0D0D5"
                          }
                        ]
                      },
                      "cornerRadius": 6,
                      "children": [
                        {
                          "id": "t-979",
                          "type": "text",
                          "content": "◉ С нуля",
                          "fontFamily": "Roboto",
                          "fontSize": 13,
                          "fontWeight": 700,
                          "fill": [
                            {
                              "type": "solid",
                              "color": "#2C2C2E"
                            }
                          ]
                        },
                        {
                          "id": "t-980",
                          "type": "text",
                          "content": "Пустая смена с настройками по умолчанию",
                          "fontFamily": "Roboto",
                          "fontSize": 11,
                          "fontWeight": 400,
                          "fill": [
                            {
                              "type": "solid",
                              "color": "#6C6C72"
                            }
                          ]
                        }
                      ]
                    },
                    {
                      "id": "box-984",
                      "type": "frame",
                      "width": "fill_container",
                      "height": "fit_content",
                      "layout": "vertical",
                      "gap": 12,
                      "padding": 16,
                      "fill": [
                        {
                          "type": "solid",
                          "color": "#FAFAFC"
                        }
                      ],
                      "stroke": {
                        "thickness": 1,
                        "fill": [
                          {
                            "type": "solid",
                            "color": "#D0D0D5"
                          }
                        ]
                      },
                      "cornerRadius": 6,
                      "children": [
                        {
                          "id": "t-982",
                          "type": "text",
                          "content": "○ Копировать существующую",
                          "fontFamily": "Roboto",
                          "fontSize": 13,
                          "fontWeight": 700,
                          "fill": [
                            {
                              "type": "solid",
                              "color": "#2C2C2E"
                            }
                          ]
                        },
                        {
                          "id": "t-983",
                          "type": "text",
                          "content": "Настройки, ачивки, шаблоны событий — без участников",
                          "fontFamily": "Roboto",
                          "fontSize": 11,
                          "fontWeight": 400,
                          "fill": [
                            {
                              "type": "solid",
                              "color": "#6C6C72"
                            }
                          ]
                        }
                      ]
                    }
                  ]
                },
                {
                  "id": "plain-989",
                  "type": "frame",
                  "width": "fill_container",
                  "height": "fit_content",
                  "layout": "vertical",
                  "gap": 6,
                  "padding": 0,
                  "children": [
                    {
                      "id": "t-986",
                      "type": "text",
                      "content": "НАЗВАНИЕ",
                      "fontFamily": "Roboto",
                      "fontSize": 11,
                      "fontWeight": 400,
                      "fill": [
                        {
                          "type": "solid",
                          "color": "#6C6C72"
                        }
                      ]
                    },
                    {
                      "id": "inp-987",
                      "type": "frame",
                      "role": "form-input",
                      "width": "fill_container",
                      "height": 36,
                      "padding": [
                        8,
                        12
                      ],
                      "layout": "horizontal",
                      "alignItems": "center",
                      "fill": [
                        {
                          "type": "solid",
                          "color": "#FFFFFF"
                        }
                      ],
                      "stroke": {
                        "thickness": 1,
                        "fill": [
                          {
                            "type": "solid",
                            "color": "#D0D0D5"
                          }
                        ]
                      },
                      "cornerRadius": 6,
                      "children": [
                        {
                          "id": "t-988",
                          "type": "text",
                          "content": "Например: ТЕЛЕМОРЕ Лето 2027",
                          "fontFamily": "Roboto",
                          "fontSize": 12,
                          "fontWeight": 400,
                          "fill": [
                            {
                              "type": "solid",
                              "color": "#B0B0B5"
                            }
                          ]
                        }
                      ]
                    }
                  ]
                },
                {
                  "id": "plain-1002",
                  "type": "frame",
                  "width": "fill_container",
                  "height": "fit_content",
                  "layout": "horizontal",
                  "gap": 12,
                  "padding": 0,
                  "children": [
                    {
                      "id": "plain-993",
                      "type": "frame",
                      "width": "fill_container",
                      "height": "fit_content",
                      "layout": "vertical",
                      "gap": 6,
                      "padding": 0,
                      "children": [
                        {
                          "id": "t-990",
                          "type": "text",
                          "content": "ДАТА НАЧАЛА",
                          "fontFamily": "Roboto",
                          "fontSize": 11,
                          "fontWeight": 400,
                          "fill": [
                            {
                              "type": "solid",
                              "color": "#6C6C72"
                            }
                          ]
                        },
                        {
                          "id": "inp-991",
                          "type": "frame",
                          "role": "form-input",
                          "width": "fill_container",
                          "height": 36,
                          "padding": [
                            8,
                            12
                          ],
                          "layout": "horizontal",
                          "alignItems": "center",
                          "fill": [
                            {
                              "type": "solid",
                              "color": "#FFFFFF"
                            }
                          ],
                          "stroke": {
                            "thickness": 1,
                            "fill": [
                              {
                                "type": "solid",
                                "color": "#D0D0D5"
                              }
                            ]
                          },
                          "cornerRadius": 6,
                          "children": [
                            {
                              "id": "t-992",
                              "type": "text",
                              "content": "10.06.2027",
                              "fontFamily": "Roboto",
                              "fontSize": 12,
                              "fontWeight": 400,
                              "fill": [
                                {
                                  "type": "solid",
                                  "color": "#B0B0B5"
                                }
                              ]
                            }
                          ]
                        }
                      ]
                    },
                    {
                      "id": "plain-997",
                      "type": "frame",
                      "width": "fill_container",
                      "height": "fit_content",
                      "layout": "vertical",
                      "gap": 6,
                      "padding": 0,
                      "children": [
                        {
                          "id": "t-994",
                          "type": "text",
                          "content": "ДАТА ОКОНЧАНИЯ",
                          "fontFamily": "Roboto",
                          "fontSize": 11,
                          "fontWeight": 400,
                          "fill": [
                            {
                              "type": "solid",
                              "color": "#6C6C72"
                            }
                          ]
                        },
                        {
                          "id": "inp-995",
                          "type": "frame",
                          "role": "form-input",
                          "width": "fill_container",
                          "height": 36,
                          "padding": [
                            8,
                            12
                          ],
                          "layout": "horizontal",
                          "alignItems": "center",
                          "fill": [
                            {
                              "type": "solid",
                              "color": "#FFFFFF"
                            }
                          ],
                          "stroke": {
                            "thickness": 1,
                            "fill": [
                              {
                                "type": "solid",
                                "color": "#D0D0D5"
                              }
                            ]
                          },
                          "cornerRadius": 6,
                          "children": [
                            {
                              "id": "t-996",
                              "type": "text",
                              "content": "23.06.2027",
                              "fontFamily": "Roboto",
                              "fontSize": 12,
                              "fontWeight": 400,
                              "fill": [
                                {
                                  "type": "solid",
                                  "color": "#B0B0B5"
                                }
                              ]
                            }
                          ]
                        }
                      ]
                    },
                    {
                      "id": "plain-1001",
                      "type": "frame",
                      "width": "fill_container",
                      "height": "fit_content",
                      "layout": "vertical",
                      "gap": 6,
                      "padding": 0,
                      "children": [
                        {
                          "id": "t-998",
                          "type": "text",
                          "content": "УЧАСТНИКОВ (MAX)",
                          "fontFamily": "Roboto",
                          "fontSize": 11,
                          "fontWeight": 400,
                          "fill": [
                            {
                              "type": "solid",
                              "color": "#6C6C72"
                            }
                          ]
                        },
                        {
                          "id": "inp-999",
                          "type": "frame",
                          "role": "form-input",
                          "width": "fill_container",
                          "height": 36,
                          "padding": [
                            8,
                            12
                          ],
                          "layout": "horizontal",
                          "alignItems": "center",
                          "fill": [
                            {
                              "type": "solid",
                              "color": "#FFFFFF"
                            }
                          ],
                          "stroke": {
                            "thickness": 1,
                            "fill": [
                              {
                                "type": "solid",
                                "color": "#D0D0D5"
                              }
                            ]
                          },
                          "cornerRadius": 6,
                          "children": [
                            {
                              "id": "t-1000",
                              "type": "text",
                              "content": "60",
                              "fontFamily": "Roboto",
                              "fontSize": 12,
                              "fontWeight": 400,
                              "fill": [
                                {
                                  "type": "solid",
                                  "color": "#B0B0B5"
                                }
                              ]
                            }
                          ]
                        }
                      ]
                    }
                  ]
                },
                {
                  "id": "plain-1007",
                  "type": "frame",
                  "width": "fill_container",
                  "height": "fit_content",
                  "layout": "horizontal",
                  "gap": 8,
                  "padding": 0,
                  "justifyContent": "end",
                  "children": [
                    {
                      "id": "btn-1003",
                      "type": "frame",
                      "role": "button",
                      "width": "fit_content",
                      "height": 36,
                      "padding": [
                        8,
                        16
                      ],
                      "layout": "horizontal",
                      "alignItems": "center",
                      "justifyContent": "center",
                      "fill": [
                        {
                          "type": "solid",
                          "color": "#FFFFFF"
                        }
                      ],
                      "stroke": {
                        "thickness": 1,
                        "fill": [
                          {
                            "type": "solid",
                            "color": "#D0D0D5"
                          }
                        ]
                      },
                      "cornerRadius": 6,
                      "children": [
                        {
                          "id": "t-1004",
                          "type": "text",
                          "content": "Отмена",
                          "fontFamily": "Roboto",
                          "fontSize": 12,
                          "fontWeight": 600,
                          "fill": [
                            {
                              "type": "solid",
                              "color": "#2C2C2E"
                            }
                          ]
                        }
                      ]
                    },
                    {
                      "id": "btn-1005",
                      "type": "frame",
                      "role": "button",
                      "width": "fit_content",
                      "height": 36,
                      "padding": [
                        8,
                        16
                      ],
                      "layout": "horizontal",
                      "alignItems": "center",
                      "justifyContent": "center",
                      "fill": [
                        {
                          "type": "solid",
                          "color": "#2C2C2E"
                        }
                      ],
                      "stroke": {
                        "thickness": 1,
                        "fill": [
                          {
                            "type": "solid",
                            "color": "#2C2C2E"
                          }
                        ]
                      },
                      "cornerRadius": 6,
                      "children": [
                        {
                          "id": "t-1006",
                          "type": "text",
                          "content": "Создать",
                          "fontFamily": "Roboto",
                          "fontSize": 12,
                          "fontWeight": 600,
                          "fill": [
                            {
                              "type": "solid",
                              "color": "#FFF"
                            }
                          ]
                        }
                      ]
                    }
                  ]
                }
              ]
            }
          ]
        }
      ]
    }
  ]
}